<?xml version="1.0" encoding="UTF-8"?>


<c3p0-config>
	<named-config name="com.shop.javaweb">
		<property name="driverClass">com.mysql.cj.jdbc.Driver</property>
		<property name="jdbcUrl">jdbc:mysql://localhost:3306/shop
		</property>
		<property name="user">root</property>
		<property name="password">mysql</property>

		<property name="initialPoolSize">5</property>
		<property name="acquireIncrement">2</property>
		<property name="minPoolSize">2</property>
		<property name="maxPoolSize">10</property>
		<property name="checkoutTimeout">3000</property>
	</named-config>
</c3p0-config>